{"clubname": "F.C. United of Manchester", "image": "https://upload.wikimedia.org/wikipedia/en/4/4d/FC_United_of_Manchester_crest.svg", "alt": "A circular badge with \"Football Club United of Manchester\" written in white capitals just inside the black circumference with a red trim. Inside is a yellow crest on a red background. The crest has a yellow ship with three sails on a white background, and three yellow stripes on a red background.", "fullname": "Football Club United of Manchester", "nickname": "F.C. United The Reds Red Rebels", "founded": "2005", "ground": "Broadhurst Park", "capacity": "4,400", "chrtitle": "Operations Manager", "chairman": "Paul Smith", "manager": "Neil Reynolds", "league": "", "season": "", "position": "", "website": "[http://www.fc-utd.co.uk/](http://www.fc-utd.co.uk/)", "current": "2021\u201322 Northern Premier League", "pattern_la1": "_whiteborder", "pattern_b1": "_vneckwhite", "pattern_ra1": "_whiteborder", "leftarm1": "FF0000", "body1": "FF0000", "rightarm1": "FF0000", "shorts1": "FFFFFF", "socks1": "000000", "pattern_la2": "_blackborder", "pattern_b2": "_vneckblack", "pattern_ra2": "_blackborder", "leftarm2": "FFFFFF", "body2": "FFFFFF", "rightarm2": "FFFFFF", "shorts2": "000000", "socks2": "FFFFFF", "pattern_la3": "_whiteborder", "pattern_b3": "_whitecollar", "pattern_ra3": "_whiteborder", "leftarm3": "0000FF", "body3": "0000FF", "rightarm3": "0000FF", "shorts3": "0000FF", "socks3": "0000FF"}