{"type": "AdaptiveCard", "$schema": "http://adaptivecards.io/schemas/adaptive-card.json", "version": "1.5", "body": [{"type": "Container", "style": "emphasis", "$data": "${' ' + '' + '\n\n'}", "$when": "${length(trim($data)) > 0}", "items": [{"type": "TextBlock", "text": "${$data}", "style": "heading", "wrap": "true", "horizontalAlignment": "Center"}]}, {"type": "Image", "horizontalAlignment": "Center", "$data": "${' ' + if(image != null, image, '') + '\n'}", "url": "${$data}", "$when": "${length(trim($data)) > 0}"}, {"type": "TextBlock", "$data": "${' ' + if(caption != null, caption, '') + '\n\n'}", "text": "${$data}", "horizontalAlignment": "Center", "$when": "${length(trim($data)) > 0}", "wrap": "true"}, {"type": "FactSet", "facts": [{"title": "${$data.title}", "$data": "${{'data': ' ' + if(alt_name != null, alt_name, '') + '\n\n', 'title': ' Also known as\n'}}", "value": "${$data.data}", "$when": "${length(trim($data.data)) > 0}"}]}, {"$data": "${' ' + if(native_name != null, native_name, '') + '\n\n'}", "$when": "${length(trim($data)) > 0}", "type": "TextBlock", "text": "${$data}", "horizontalAlignment": "Center"}, {"type": "FactSet", "facts": [{"title": "${$data.title}", "$data": "${{'data': ' ' + if(genre != null, genre, '') + '\n\n', 'title': ' Genre\n'}}", "value": "${$data.data}", "$when": "${length(trim($data.data)) > 0}"}, {"title": "${$data.title}", "$data": "${{'data': ' ' + if(creator != null, creator, '') + '\n\n', 'title': ' Created by\n'}}", "value": "${$data.data}", "$when": "${length(trim($data.data)) > 0}"}, {"title": "${$data.title}", "$data": "${{'data': ' ' + if(based_on != null, based_on, '') + ' ' + '\n\n', 'title': ' ' + if(trim(if(based_on != null, based_on, '')) != '', ' Based on ', ' Inspired by ') + '\n'}}", "value": "${$data.data}", "$when": "${length(trim($data.data)) > 0}"}, {"title": "${$data.title}", "$data": "${{'data': ' ' + if(developer != null, developer, '') + '\n\n', 'title': ' Developed by\n'}}", "value": "${$data.data}", "$when": "${length(trim($data.data)) > 0}"}, {"title": "${$data.title}", "$data": "${{'data': ' ' + if(writer != null, writer, '') + '\n\n', 'title': ' Written by\n'}}", "value": "${$data.data}", "$when": "${length(trim($data.data)) > 0}"}, {"title": "${$data.title}", "$data": "${{'data': ' ' + if(screenplay != null, screenplay, '') + '\n\n', 'title': ' Screenplay by\n'}}", "value": "${$data.data}", "$when": "${length(trim($data.data)) > 0}"}, {"title": "${$data.title}", "$data": "${{'data': ' ' + if(story != null, story, '') + '\n\n', 'title': ' Story by\n'}}", "value": "${$data.data}", "$when": "${length(trim($data.data)) > 0}"}, {"title": "${$data.title}", "$data": "${{'data': ' ' + if(director != null, director, '') + '\n\n', 'title': ' Directed by\n'}}", "value": "${$data.data}", "$when": "${length(trim($data.data)) > 0}"}, {"title": "${$data.title}", "$data": "${{'data': ' ' + if(creative_director != null, creative_director, '') + '\n\n', 'title': ' Creative director' + '' + '\n'}}", "value": "${$data.data}", "$when": "${length(trim($data.data)) > 0}"}, {"title": "${$data.title}", "$data": "${{'data': ' ' + if(presenter != null, presenter, '') + ' ' + '\n\n', 'title': ' Presented by\n'}}", "value": "${$data.data}", "$when": "${length(trim($data.data)) > 0}"}, {"title": "${$data.title}", "$data": "${{'data': ' ' + if(starring != null, starring, '') + '\n\n', 'title': ' Starring\n'}}", "value": "${$data.data}", "$when": "${length(trim($data.data)) > 0}"}, {"title": "${$data.title}", "$data": "${{'data': ' ' + if(judges != null, judges, '') + '\n\n', 'title': ' Judges\n'}}", "value": "${$data.data}", "$when": "${length(trim($data.data)) > 0}"}, {"title": "${$data.title}", "$data": "${{'data': ' ' + if(voices != null, voices, '') + '\n\n', 'title': ' Voices of\n'}}", "value": "${$data.data}", "$when": "${length(trim($data.data)) > 0}"}, {"title": "${$data.title}", "$data": "${{'data': ' ' + if(narrated != null, narrated, '') + '\n\n', 'title': ' Narrated by\n'}}", "value": "${$data.data}", "$when": "${length(trim($data.data)) > 0}"}, {"title": "${$data.title}", "$data": "${{'data': ' ' + if(theme_music_composer != null, theme_music_composer, '') + ' ' + '\n\n', 'title': ' ' + if(trim(if(music != null, music, '')) != '', ' Music by ', ' Theme music composer ') + '\n'}}", "value": "${$data.data}", "$when": "${length(trim($data.data)) > 0}"}, {"title": "${$data.title}", "$data": "${{'data': ' ' + if(open_theme != null, open_theme, '') + ' ' + '\n\n', 'title': ' Opening theme\n'}}", "value": "${$data.data}", "$when": "${length(trim($data.data)) > 0}"}, {"title": "${$data.title}", "$data": "${{'data': ' ' + if(end_theme != null, end_theme, '') + ' ' + '\n\n', 'title': ' Ending theme\n'}}", "value": "${$data.data}", "$when": "${length(trim($data.data)) > 0}"}, {"title": "${$data.title}", "$data": "${{'data': ' ' + if(composer != null, composer, '') + '\n\n', 'title': ' Composer' + '' + '\n'}}", "value": "${$data.data}", "$when": "${length(trim($data.data)) > 0}"}, {"title": "${$data.title}", "$data": "${{'data': ' ' + if(country != null, country, '') + '\n\n', 'title': ' Country of origin\n'}}", "value": "${$data.data}", "$when": "${length(trim($data.data)) > 0}"}, {"title": "${$data.title}", "$data": "${{'data': ' ' + if(language != null, language, '') + '\n\n', 'title': ' Original language' + '' + '\n'}}", "value": "${$data.data}", "$when": "${length(trim($data.data)) > 0}"}, {"title": "${$data.title}", "$data": "${{'data': ' ' + if(num_seasons != null, num_seasons, '') + ' ' + '\n\n', 'title': ' ' + 'No.' + ' of ' + if(trim(if(num_seasons != null, num_seasons, '')) != '', ' seasons ', ' series ') + '\n'}}", "value": "${$data.data}", "$when": "${length(trim($data.data)) > 0}"}, {"title": "${$data.title}", "$data": "${{'data': ' ' + if(if(name != null, name, '') == ' Doctor Who ', ' ' + if(num_series != null, num_series, '') + ' ', '') + '\n\n', 'title': ' ' + if(if(name != null, name, '') == ' Doctor Who ', ' ' + 'No.' + ' of series ', '') + '\n'}}", "value": "${$data.data}", "$when": "${length(trim($data.data)) > 0}"}, {"title": "${$data.title}", "$data": "${{'data': ' ' + if(num_episodes != null, num_episodes, '') + ' ' + if(trim(if(list_episodes != null, list_episodes, '')) != '', ' ' + '(' + 'list of episodes' + ')' + ' ', '') + '\n\n', 'title': ' ' + 'No.' + ' of episodes\n'}}", "value": "${$data.data}", "$when": "${length(trim($data.data)) > 0}"}]}, {"type": "Container", "style": "emphasis", "wrap": "true", "$data": "${' Production\n\n'}", "$when": "${length(trim($data)) > 0}", "items": [{"type": "TextBlock", "text": "${$data}", "weight": "Bolder", "horizontalAlignment": "Center"}]}, {"type": "FactSet", "facts": [{"title": "${$data.title}", "$data": "${{'data': ' ' + if(executive_producer != null, executive_producer, '') + '\n\n', 'title': ' Executive producer' + '' + '\n'}}", "value": "${$data.data}", "$when": "${length(trim($data.data)) > 0}"}, {"title": "${$data.title}", "$data": "${{'data': ' ' + if(producer != null, producer, '') + '\n\n', 'title': ' Producer' + '' + '\n'}}", "value": "${$data.data}", "$when": "${length(trim($data.data)) > 0}"}, {"title": "${$data.title}", "$data": "${{'data': ' ' + if(news_editor != null, news_editor, '') + '\n\n', 'title': ' News editor' + '' + '\n'}}", "value": "${$data.data}", "$when": "${length(trim($data.data)) > 0}"}, {"title": "${$data.title}", "$data": "${{'data': ' ' + if(location != null, location, '') + '\n\n', 'title': ' Production location' + '' + '\n'}}", "value": "${$data.data}", "$when": "${length(trim($data.data)) > 0}"}, {"title": "${$data.title}", "$data": "${{'data': ' ' + if(cinematography != null, cinematography, '') + '\n\n', 'title': ' Cinematography\n'}}", "value": "${$data.data}", "$when": "${length(trim($data.data)) > 0}"}, {"title": "${$data.title}", "$data": "${{'data': ' ' + if(animator != null, animator, '') + '\n\n', 'title': ' Animator' + '' + '\n'}}", "value": "${$data.data}", "$when": "${length(trim($data.data)) > 0}"}, {"title": "${$data.title}", "$data": "${{'data': ' ' + if(editor != null, editor, '') + '\n\n', 'title': ' Editor' + '' + '\n'}}", "value": "${$data.data}", "$when": "${length(trim($data.data)) > 0}"}, {"title": "${$data.title}", "$data": "${{'data': ' ' + if(camera != null, camera, '') + '\n\n', 'title': ' Camera setup\n'}}", "value": "${$data.data}", "$when": "${length(trim($data.data)) > 0}"}, {"title": "${$data.title}", "$data": "${{'data': ' ' + if(runtime != null, runtime, '') + '\n\n', 'title': ' Running time\n'}}", "value": "${$data.data}", "$when": "${length(trim($data.data)) > 0}"}, {"title": "${$data.title}", "$data": "${{'data': ' ' + if(company != null, company, '') + ' ' + '\n\n', 'title': ' Production ' + '' + '\n'}}", "value": "${$data.data}", "$when": "${length(trim($data.data)) > 0}"}, {"title": "${$data.title}", "$data": "${{'data': ' ' + if(distributor != null, distributor, '') + '\n\n', 'title': ' Distributor\n'}}", "value": "${$data.data}", "$when": "${length(trim($data.data)) > 0}"}, {"title": "${$data.title}", "$data": "${{'data': ' ' + if(budget != null, budget, '') + '\n\n', 'title': ' Budget\n'}}", "value": "${$data.data}", "$when": "${length(trim($data.data)) > 0}"}]}, {"type": "Container", "style": "emphasis", "wrap": "true", "$data": "${' Release\n\n'}", "$when": "${length(trim($data)) > 0}", "items": [{"type": "TextBlock", "text": "${$data}", "weight": "Bolder", "horizontalAlignment": "Center"}]}, {"type": "FactSet", "facts": [{"title": "${$data.title}", "$data": "${{'data': ' ' + if(network != null, network, '') + ' ' + '\n\n', 'title': ' Original network\n'}}", "value": "${$data.data}", "$when": "${length(trim($data.data)) > 0}"}, {"title": "${$data.title}", "$data": "${{'data': ' ' + if(picture_format != null, picture_format, '') + '\n\n', 'title': ' Picture format\n'}}", "value": "${$data.data}", "$when": "${length(trim($data.data)) > 0}"}, {"title": "${$data.title}", "$data": "${{'data': ' ' + if(audio_format != null, audio_format, '') + '\n\n', 'title': ' Audio format\n'}}", "value": "${$data.data}", "$when": "${length(trim($data.data)) > 0}"}, {"title": "${$data.title}", "$data": "${{'data': ' ' + if(first_run != null, first_run, '') + '\n\n', 'title': ' First shown in\n'}}", "value": "${$data.data}", "$when": "${length(trim($data.data)) > 0}"}, {"title": "${$data.title}", "$data": "${{'data': ' ' + '' + '\n\n', 'title': ' Original release\n'}}", "value": "${$data.data}", "$when": "${length(trim($data.data)) > 0}"}]}, {"type": "Container", "style": "emphasis", "wrap": "true", "$data": "${' Chronology\n\n'}", "$when": "${length(trim($data)) > 0}", "items": [{"type": "TextBlock", "text": "${$data}", "weight": "Bolder", "horizontalAlignment": "Center"}]}, {"type": "FactSet", "facts": [{"title": "${$data.title}", "$data": "${{'data': ' ' + if(preceded_by != null, preceded_by, '') + '\n\n', 'title': ' Preceded by\n'}}", "value": "${$data.data}", "$when": "${length(trim($data.data)) > 0}"}, {"title": "${$data.title}", "$data": "${{'data': ' ' + if(followed_by != null, followed_by, '') + '\n\n', 'title': ' Followed by\n'}}", "value": "${$data.data}", "$when": "${length(trim($data.data)) > 0}"}, {"title": "${$data.title}", "$data": "${{'data': ' ' + if(related != null, related, '') + '\n\n', 'title': ' Related shows\n'}}", "value": "${$data.data}", "$when": "${length(trim($data.data)) > 0}"}]}], "actions": [{"type": "Action.OpenUrl", "title": "Wikipedia", "url": "https://en.wikipedia.org/wiki/Squid_Game"}]}